{
  "businesses": [
    {
      "id": 1,
      "name": "Roots Southern Table",
      "category": "Food & Beverage",
      "description": "Roots Southern Table pays homage to the way Chef Tiffany Derry grew up eating in the South. The restaurant emphasizes field-to-table eating, reflecting a lifestyle of eating with the seasons, canning, and preserving fresh-picked fruits and vegetables. Signature dishes include Duck-Fat Fried Chicken, Texas Red Fish, and My Mother's Gumbo.",
      "location": "13050 Bee Street, Suite 160, Farmers Branch, TX 75234",
      "coordinates": [32.9225, -96.8966],
      "phone": "214-346-4441",
      "email": "info@rootssoutherntable.com",
      "website": "https://www.rootssoutherntable.com/",
      "hours": "Tuesday to Sunday, 5:00 PM – 10:00 PM ",
      "imageUrl": "https://static.wixstatic.com/media/ddebe1_c5a79d14f5bd45d09cbd2e4af797d199~mv2.png"
    }
  ]
}